llama_index/packs/infer_retrieve_rerank/__init__.py
llama_index/packs/infer_retrieve_rerank/base.py
llama_index_packs_infer_retrieve_rerank-0.5.1.dist-info/METADATA
llama_index_packs_infer_retrieve_rerank-0.5.1.dist-info/WHEEL
llama_index_packs_infer_retrieve_rerank-0.5.1.dist-info/licenses/LICENSE
llama_index_packs_infer_retrieve_rerank-0.5.1.dist-info/RECORD
