Metadata-Version: 2.4
Name: llama-index-packs-infer-retrieve-rerank
Version: 0.5.1
Summary: llama-index packs infer retrieve rerank integration
Author-email: Your Name <you@example.com>
Maintainer: jerryjliu
License-Expression: MIT
License-File: LICENSE
Keywords: infer,rag,rerank,retrieve,retriever
Requires-Python: <4.0,>=3.9
Requires-Dist: llama-index-core<0.13,>=0.12.0
Requires-Dist: llama-index-embeddings-openai<0.4,>=0.3.0
Requires-Dist: llama-index-llms-openai<0.5,>=0.4.0
Requires-Dist: llama-index-postprocessor-rankgpt-rerank<0.4,>=0.3.0
